{"trial_id": "04", "hyperparameters": {"space": [{"class_name": "Choice", "config": {"name": "batch_size", "default": 32, "conditions": [], "values": [32, 64, 128], "ordered": true}}, {"class_name": "Choice", "config": {"name": "rnn_layers", "default": 2, "conditions": [], "values": [2, 3], "ordered": true}}, {"class_name": "Choice", "config": {"name": "units", "default": 32, "conditions": [], "values": [32, 64, 128], "ordered": true}}, {"class_name": "Choice", "config": {"name": "activation", "default": "relu", "conditions": [], "values": ["relu", "tanh"], "ordered": false}}, {"class_name": "Choice", "config": {"name": "dropout", "default": 0.08, "conditions": [], "values": [0.08, 0.2], "ordered": true}}, {"class_name": "Choice", "config": {"name": "clipvalue", "default": 0.01, "conditions": [], "values": [0.01, 0.1, 1.0], "ordered": true}}], "values": {"batch_size": 32, "rnn_layers": 3, "units": 32, "activation": "relu", "dropout": 0.08, "clipvalue": 0.1}}, "metrics": {"metrics": {"loss": {"direction": "min", "observations": [{"value": [0.03814323991537094], "step": 0}]}, "mse": {"direction": "min", "observations": [{"value": [0.03814323991537094], "step": 0}]}, "val_loss": {"direction": "min", "observations": [{"value": [0.007107627112418413], "step": 0}]}, "val_mse": {"direction": "min", "observations": [{"value": [0.007107627112418413], "step": 0}]}}}, "score": 0.007107627112418413, "best_step": 0, "status": "COMPLETED", "message": null}